setup.py
tumblr.py
TumblrAPI.egg-info/PKG-INFO
TumblrAPI.egg-info/SOURCES.txt
TumblrAPI.egg-info/dependency_links.txt
TumblrAPI.egg-info/top_level.txt