Metadata-Version: 1.1
Name: TumblrAPI
Version: 0.2.4
Summary: Tumblr API client for Python
Home-page: http://labs.spaceshipnofuture.org/tumblrapi/
Author: SNF Labs
Author-email: jacob@spaceshipnofuture.org
License: MIT
Keywords: tumblr api webservice parser
Platform: UNKNOWN
Classifier: Development Status :: 4 - Beta
Classifier: License :: OSI Approved :: MIT License
Classifier: Programming Language :: Python
Classifier: Operating System :: OS Independent
Classifier: Intended Audience :: Developers
Classifier: Topic :: Software Development :: Libraries :: Python Modules
Classifier: Topic :: Internet
Requires: httplib2 (>= 0.2)
Requires: ElementTree (>= 1.2)
